djjsmin
