Metadata-Version: 1.0
Name: django-jsmin
Version: 0.2
Summary: JavaScript library minification for Django.
Home-page: http://bitbucket.org/zacharyvoase/django-jsmin
Author: Zachary Voase
Author-email: zacharyvoase@me.com
License: UNKNOWN
Platform: UNKNOWN
